{
    "paths": {
        "/userinfo": {
            "get": {
                "x-auth-type": "Application & Application User",
                "summary": "Get User Info",
                "x-throttling-tier": "Unlimited",
                "description": "Implementation of the OpenID Connect Userinfo spec. Can return results as a signed JWT or a plain JSON structure.",
                "produces": [
                    "application/json",
                    "application/jwt"
                ],
                "parameters": [
                    {
                        "description": "Must be 'openid'",
                        "name": "schema",
                        "type": "string",
                        "required": true,
                        "in": "query"
                    }
                ],
                "responses": {
                    "200": {}
                }
            }
        }
    },
    "swagger": "2.0",
    "info": {
        "title": "OpenID-Userinfo",
        "version": "stg"
    },
    "basePath": "/openid-userinfo/stg",
    "host": "api.byu.edu:443"
}